photpy/__init__.py
photpy/components/__init__.py
photpy/components/adaptive_equalizer.py
photpy/components/ber.py
photpy/components/bps.py
photpy/components/dac_noise.py
photpy/components/frame_syncer.py
photpy/components/gaussian_noise.py
photpy/components/modem.py
photpy/components/phase_noise.py
photpy/components/pulse_shaping.py
photpy/components/rx_simple.py
photpy/optical/__init__.py
photpy/optical/awgn.py
photpy/optical/bit_error.py
photpy/optical/bps.py
photpy/optical/cma_rde.py
photpy/optical/fine_sync.py
photpy/optical/linewidth_noise.py
photpy/optical/offset_compens.py
photpy/optical/orthog.py
photpy/optical/resolution.py
photpy/utils/__init__.py
photpy/utils/dsp.py
photpy/utils/gpu.py
photpy/utils/io.py
photpy/utils/logging.py
photpy/utils/mathutils.py
photpy/utils/plot.py
photpy-0.2.dist-info/METADATA
photpy-0.2.dist-info/WHEEL
photpy-0.2.dist-info/RECORD
