Metadata-Version: 2.1
Name: photpy
Version: 0.2
Summary: A Python library for the simulation of optical fiber transmission
Project-URL: Homepage, https://gitee.com/opticalab_1/pyphot
Author-email: Chunyu Li <cyli0212@gmail.com>
Requires-Python: >=3.7
Requires-Dist: matplotlib>=3.5.2
Requires-Dist: numba>=0.55.2
Requires-Dist: numpy>=1.22.4
Requires-Dist: scikit-commpy>=0.7.0
Requires-Dist: scipy>=1.8.1
